{
  "_id": "2i7iadib5QZf8Z2hekfnso",
  "_createdAt": "2025-11-02T00:03:05Z",
  "_updatedAt": "2025-11-02T20:56:33Z",
  "title": "Samantha Tan's Strategic Vision Transforms Motorsport Industry Dynamics",
  "slug": "samantha-tans-strategic-vision-transforms-motorsport-industry-dynamics",
  "excerpt": null,
  "isFeatured": false,
  "readTime": 8,
  "wordCount": 1450,
  "views": 2438031,
  "author": {
    "name": "Aisha Farouk",
    "slug": {
      "_type": "slug",
      "current": "aisha-farouk"
    }
  },
  "categories": [
    {
      "slug": {
        "_type": "slug",
        "current": "innovation"
      },
      "title": "Innovation"
    }
  ],
  "mainImage": {
    "alt": "Samantha Tan's Strategic Vision Transforms Motorsport Industry Dynamics",
    "asset": {
      "_id": "image-2cfa9bc1610a229e86bddc84e7544d815721a6ab-1200x800-jpg",
      "url": "https://cdn.sanity.io/images/2f93fcy8/production/2cfa9bc1610a229e86bddc84e7544d815721a6ab-1200x800.jpg"
    }
  },
  "body": [
    {
      "_type": "block",
      "children": [
        {
          "_type": "span",
          "marks": [],
          "text": "Samantha Tan's Strategic Vision Transforms Motorsport Industry Dynamics"
        }
      ],
      "markDefs": [],
      "style": "normal"
    },
    {
      "_type": "block",
      "children": [
        {
          "_type": "span",
          "marks": [],
          "text": "In the fast-paced world of motorsport, where milliseconds can make or break a career, Samantha Tan is redefining what it means to be a leader—both on and off the track. At just 27 years old, this Chinese Canadian driver has not only carved out a name for herself in one of the most demanding sporting arenas but also transformed the landscape of endurance racing through her innovative approach to team ownership and strategic execution."
        }
      ],
      "markDefs": [],
      "style": "normal"
    },
    {
      "_type": "block",
      "children": [
        {
          "_type": "span",
          "marks": [],
          "text": "Tan recently returned from an emotionally charged weekend at the legendary Circuit de la Sarthe, where she made her debut in the Road to Le Mans races—a pair of two-hour support events leading up to the iconic 24 Hours of Le Mans. It was a milestone moment, marking her first time behind the wheel on the famed French circuit after years spent watching from the sidelines. Racing alongside Swedish driver Gustav Bergstrom for BMW team WRT in a BMW M4 GT3, Tan delivered a performance that turned heads across the paddock."
        }
      ],
      "markDefs": [],
      "style": "normal"
    },
    {
      "_type": "block",
      "children": [
        {
          "_type": "span",
          "marks": [],
          "text": "Though she faced setbacks during the races, including some unfortunate timing that impacted her results, Tan emerged with her sights firmly set on the future. “It was a rewarding and special weekend for me,” she reflected, her voice tinged with both pride and determination. “I got so emotional on the first day—it was the biggest step I’ve taken toward my ultimate goal.”"
        }
      ],
      "markDefs": [],
      "style": "normal"
    },
    {
      "_type": "block",
      "children": [
        {
          "_type": "span",
          "marks": [],
          "text": "That goal? To become the first Asian woman to win the 24 Hours of Le Mans—an achievement that would not only rewrite the record books but also inspire a new generation of racers around the globe."
        }
      ],
      "markDefs": [],
      "style": "normal"
    },
    {
      "_type": "block",
      "children": [
        {
          "_type": "span",
          "marks": [],
          "text": "From Spectator to Driver: A Journey Years in the Making"
        }
      ],
      "markDefs": [],
      "style": "normal"
    },
    {
      "_type": "block",
      "children": [
        {
          "_type": "span",
          "marks": [],
          "text": "While many drivers dream of racing at Le Mans, few have taken such deliberate steps to turn that dream into reality. Tan’s journey to the top tier of global motorsport began long before she ever set foot in a race car. Her entry into racing wasn’t accidental—it was calculated, driven by a clear vision and unwavering commitment."
        }
      ],
      "markDefs": [],
      "style": "normal"
    },
    {
      "_type": "block",
      "children": [
        {
          "_type": "span",
          "marks": [],
          "text": "At the age of 16, Tan obtained her racing license, setting her on a path that would eventually lead to the formation of her own racing team just four years later. In 2017, alongside her father Kenneth, she launched Samantha Tan Racing (STR), a bold move that distinguished her early in a sport dominated by established names and deep-pocketed organizations."
        }
      ],
      "markDefs": [],
      "style": "normal"
    },
    {
      "_type": "block",
      "children": [
        {
          "_type": "span",
          "marks": [],
          "text": "“I knew that if I wanted to make a real impact, I had to be more than just a driver,” she says. “I had to be part of the decision-making process, understand every aspect of the business, and build something that could compete at the highest level.”"
        }
      ],
      "markDefs": [],
      "style": "normal"
    },
    {
      "_type": "block",
      "children": [
        {
          "_type": "span",
          "marks": [],
          "text": "The decision to found her own team was not without risks. Starting a racing operation requires significant financial investment, logistical coordination, and a deep understanding of the technical intricacies of motorsport. But for Tan, these challenges were simply part of the equation. She approached team ownership with the same meticulous attention to detail that she applies to driving—one that prioritizes consistency, adaptability, and long-term growth over short-term wins."
        }
      ],
      "markDefs": [],
      "style": "normal"
    },
    {
      "_type": "block",
      "children": [
        {
          "_type": "span",
          "marks": [],
          "text": "Building a Legacy Through Strategic Excellence"
        }
      ],
      "markDefs": [],
      "style": "normal"
    },
    {
      "_type": "block",
      "children": [
        {
          "_type": "span",
          "marks": [],
          "text": "Under Tan’s leadership, STR has become a formidable force in international motorsport. Since its inception, the team has consistently delivered results that have elevated its status within the industry. In 2019 and 2020, STR claimed back-to-back titles in the Pirelli World Challenge and Pirelli GT4 America series, establishing itself as a dominant presence in North American racing."
        }
      ],
      "markDefs": [],
      "style": "normal"
    },
    {
      "_type": "block",
      "children": [
        {
          "_type": "span",
          "marks": [],
          "text": "The team’s ambitions didn’t stop there. In 2021, STR ventured into European competition, entering the highly competitive 24H Series. That year, they captured the overall championship in their inaugural season outside North America—a testament to their ability to adapt and thrive in unfamiliar territory."
        }
      ],
      "markDefs": [],
      "style": "normal"
    },
    {
      "_type": "block",
      "children": [
        {
          "_type": "span",
          "marks": [],
          "text": "But perhaps no achievement has been more symbolic of STR’s rise than their historic victory at the 2022 12H Mugello in Italy. Competing in the GT3 class, the team became the first-ever overall winner for BMW’s newly introduced M4 GT3, securing a coveted spot on the starting grid for the 24 Hours of Spa in Belgium. The win not only validated STR’s technical prowess but also signaled their arrival as a global contender."
        }
      ],
      "markDefs": [],
      "style": "normal"
    },
    {
      "_type": "block",
      "children": [
        {
          "_type": "span",
          "marks": [],
          "text": "Since then, the team has continued to build momentum, racking up victories at prestigious events like the GTWC Road America and the GTWC 3H Barcelona in 2023. Last year, they came agonizingly close to claiming the GTWC America championship, losing by a single point in a dramatic season finale. For Tan, the experience was bittersweet—a reminder of how thin the margins can be in motorsport, but also a source of motivation for what lies ahead."
        }
      ],
      "markDefs": [],
      "style": "normal"
    },
    {
      "_type": "block",
      "children": [
        {
          "_type": "span",
          "marks": [],
          "text": "“It’s all about perspective,” she says. “Losing by one point hurts, but it also shows how close we are to achieving something truly special. We’re not just chasing wins—we’re building a legacy.”"
        }
      ],
      "markDefs": [],
      "style": "normal"
    },
    {
      "_type": "block",
      "children": [
        {
          "_type": "span",
          "marks": [],
          "text": "Endurance as a Catalyst for Growth"
        }
      ],
      "markDefs": [],
      "style": "normal"
    },
    {
      "_type": "block",
      "children": [
        {
          "_type": "span",
          "marks": [],
          "text": "One of the defining characteristics of Tan’s career has been her unwavering focus on endurance racing. While many drivers gravitate toward sprint races, where speed and raw power dominate, Tan has chosen a different path—one that demands sustained performance, strategic thinking, and mental resilience."
        }
      ],
      "markDefs": [],
      "style": "normal"
    },
    {
      "_type": "block",
      "children": [
        {
          "_type": "span",
          "marks": [],
          "text": "Endurance racing is often described as the ultimate test of a driver’s capabilities. Unlike shorter formats, where mistakes can sometimes be corrected, endurance events require a level of consistency that leaves little room for error. Every lap counts, every decision matters, and every second must be optimized."
        }
      ],
      "markDefs": [],
      "style": "normal"
    },
    {
      "_type": "block",
      "children": [
        {
          "_type": "span",
          "marks": [],
          "text": "For Tan, this environment has proven to be the perfect breeding ground for growth—not just as a driver, but as a team owner and strategist. “Endurance racing forces you to think differently,” she explains. “You can’t rely solely on speed. You have to factor in reliability, pit strategy, tire management, fuel efficiency—it’s chess on wheels.”"
        }
      ],
      "markDefs": [],
      "style": "normal"
    },
    {
      "_type": "block",
      "children": [
        {
          "_type": "span",
          "marks": [],
          "text": "This holistic approach to racing has allowed STR to punch above its weight. As a relatively small team based in Canada, they lack the massive budgets and resources of some of their European counterparts. But what they have in spades is ingenuity, teamwork, and an unrelenting pursuit of excellence."
        }
      ],
      "markDefs": [],
      "style": "normal"
    },
    {
      "_type": "block",
      "children": [
        {
          "_type": "span",
          "marks": [],
          "text": "“We’ve built our success on strategy, consistency, and grit,” Tan says. “Those are the things that separate good teams from great ones.”"
        }
      ],
      "markDefs": [],
      "style": "normal"
    },
    {
      "_type": "block",
      "children": [
        {
          "_type": "span",
          "marks": [],
          "text": "The Road Ahead: Challenges and Opportunities"
        }
      ],
      "markDefs": [],
      "style": "normal"
    },
    {
      "_type": "block",
      "children": [
        {
          "_type": "span",
          "marks": [],
          "text": "With a packed 2025 race calendar, Tan shows no signs of slowing down. Following her debut at Le Mans, she’s preparing for another grueling challenge: the 24 Hours of Nürburgring in Germany. Known for its punishing layout and unpredictable weather, the Nürburgring is considered one of the most difficult endurance races in the world."
        }
      ],
      "markDefs": [],
      "style": "normal"
    },
    {
      "_type": "block",
      "children": [
        {
          "_type": "span",
          "marks": [],
          "text": "For Tan, it’s yet another opportunity to test herself against the best in the business—and to continue pushing the boundaries of what’s possible in motorsport."
        }
      ],
      "markDefs": [],
      "style": "normal"
    },
    {
      "_type": "block",
      "children": [
        {
          "_type": "span",
          "marks": [],
          "text": "Beyond the track, Tan is also focused on expanding STR’s influence within the industry. She’s actively working to develop partnerships with sponsors, manufacturers, and other stakeholders who share her vision for the future of racing. At the same time, she remains committed to promoting diversity and inclusion within motorsport, using her platform to advocate for greater representation of women and underrepresented communities."
        }
      ],
      "markDefs": [],
      "style": "normal"
    },
    {
      "_type": "block",
      "children": [
        {
          "_type": "span",
          "marks": [],
          "text": "“I believe that motorsport should reflect the world we live in,” she says. “There’s talent everywhere, but too often it goes unnoticed because of systemic barriers. If I can help break down those barriers, even in a small way, then that’s a victory worth celebrating.”"
        }
      ],
      "markDefs": [],
      "style": "normal"
    },
    {
      "_type": "block",
      "children": [
        {
          "_type": "span",
          "marks": [],
          "text": "Leading by Example: A Vision for the Future"
        }
      ],
      "markDefs": [],
      "style": "normal"
    },
    {
      "_type": "block",
      "children": [
        {
          "_type": "span",
          "marks": [],
          "text": "What sets Samantha Tan apart is not just her skill behind the wheel, but her ability to see the bigger picture. She understands that success in motorsport is not just about individual achievements—it’s about creating sustainable systems, nurturing talent, and driving innovation."
        }
      ],
      "markDefs": [],
      "style": "normal"
    },
    {
      "_type": "block",
      "children": [
        {
          "_type": "span",
          "marks": [],
          "text": "As she looks toward the future, Tan envisions a motorsport industry that is more inclusive, technologically advanced, and strategically aligned with the needs of the modern world. And she’s determined to play a central role in shaping that future."
        }
      ],
      "markDefs": [],
      "style": "normal"
    },
    {
      "_type": "block",
      "children": [
        {
          "_type": "span",
          "marks": [],
          "text": "“Motorsport has always been about pushing limits,” she says. “But now, it’s also about pushing boundaries—breaking down old ways of thinking and embracing new possibilities. That’s what excites me.”"
        }
      ],
      "markDefs": [],
      "style": "normal"
    },
    {
      "_type": "block",
      "children": [
        {
          "_type": "span",
          "marks": [],
          "text": "Through her dual roles as driver and team owner, Tan has already begun to redefine what it means to be a leader in the sport. She’s shown that success doesn’t always come from having the biggest budget or the most famous name—but from having a clear vision, a relentless work ethic, and the courage to take calculated risks."
        }
      ],
      "markDefs": [],
      "style": "normal"
    },
    {
      "_type": "block",
      "children": [
        {
          "_type": "span",
          "marks": [],
          "text": "As she continues to chase her dream of winning the 24 Hours of Le Mans, one thing is certain: Samantha Tan is not just racing for herself. She’s racing for everyone who believes that passion, perseverance, and purpose can overcome any obstacle."
        }
      ],
      "markDefs": [],
      "style": "normal"
    },
    {
      "_type": "block",
      "children": [
        {
          "_type": "span",
          "marks": [],
          "text": "And in doing so, she’s transforming the very dynamics of the motorsport industry—one lap at a time."
        }
      ],
      "markDefs": [],
      "style": "normal"
    }
  ],
  "writerSlug": "aisha-farouk"
}
